<?xml version="1.0" encoding="UTF-8"?>
<List>
<url title=" Episodes 578(ES) " data="http://llphotos.twitvid.com/twitvidvideosv2/0/6/C/06CXS.mp4"  thumbnail="578"></url>
<url title=" Episodes 577(ES) " data="http://llphotos.twitvid.com/twitvidvideosv2/2/6/0/260H0.mp4"  thumbnail="577"></url>
<url title=" Episodes 576(ES) " data="http://llphotos.twitvid.com/twitvidvideosv2/4/6/7/467US.mp4"  thumbnail="576"></url>
<url title=" Episodes 575(ES) " data="http://llphotos.twitvid.com/twitvidvideosv2/0/G/4/0G4X5.mp4"  thumbnail="575"></url>
<url title=" Episodes 574(ES) " data="http://llphotos.twitvid.com/twitvidvideosv2/3/5/V/35VAU.mp4"  thumbnail="574"></url>
<url title=" Episodes 573(ES) " data="http://llphotos.twitvid.com/twitvidvideosv2/7/R/J/7RJCK.mp4"  thumbnail="573"></url>
<url title=" Episodes 572(ES) " data="http://llphotos.twitvid.com/twitvidvideosv2/9/D/4/9D4XW.mp4"  thumbnail="572"></url>
<url title=" Episodes 571(ES) " data="http://llphotos.twitvid.com/twitvidvideosv2/H/S/P/HSP1V.mp4"  thumbnail="571"></url>
<url title=" Episodes 570(ES) " data="http://llphotos.twitvid.com/twitvidvideosv2/P/B/S/PBS6O.mp4"  thumbnail="570"></url>
<url title=" Episodes 569(ES) " data="http://llphotos.twitvid.com/twitvidvideosv2/J/L/7/JL7GY.mp4"  thumbnail="569"></url>
<url title=" Episodes 568(ES) " data="http://llphotos.twitvid.com/twitvidvideosv2/H/O/X/HOXMD.mp4"  thumbnail="568"></url>
<url title=" Episodes 567(ES) " data="http://f1.yucache.net/users/9e25ac98d48934216e108f48c00379a5/op567.mp4"  thumbnail="567"></url>
<url title=" Episodes 566(ES) " data="http://llphotos.twitvid.com/twitvidvideosv2/M/S/W/MSWD9.mp4"  thumbnail="566"></url>
<url title=" Episodes 565(ES) " data="http://llphotos.twitvid.com/twitvidvideosv2/D/4/T/D4TEM.mp4"  thumbnail="565"></url>

</List>
